supermarq/__init__.py
supermarq/_version.py
supermarq/_version_test.py
supermarq/benchmark.py
supermarq/benchmark_test.py
supermarq/features.py
supermarq/features_test.py
supermarq/plotting.py
supermarq/plotting_test.py
supermarq/py.typed
supermarq/simulation.py
supermarq/stabilizers.py
supermarq/benchmarks/__init__.py
supermarq/benchmarks/bit_code.py
supermarq/benchmarks/bit_code_test.py
supermarq/benchmarks/ghz.py
supermarq/benchmarks/ghz_test.py
supermarq/benchmarks/hamiltonian_simulation.py
supermarq/benchmarks/hamiltonian_simulation_test.py
supermarq/benchmarks/mermin_bell.py
supermarq/benchmarks/mermin_bell_test.py
supermarq/benchmarks/phase_code.py
supermarq/benchmarks/phase_code_test.py
supermarq/benchmarks/qaoa_fermionic_swap_proxy.py
supermarq/benchmarks/qaoa_fermionic_swap_proxy_test.py
supermarq/benchmarks/qaoa_vanilla_proxy.py
supermarq/benchmarks/qaoa_vanilla_proxy_test.py
supermarq/benchmarks/vqe_proxy.py
supermarq/benchmarks/vqe_proxy_test.py
supermarq/converters/__init__.py
supermarq/converters/qiskit.py
supermarq/converters/qiskit_test.py
supermarq/qcvv/__init__.py
supermarq/qcvv/base_experiment.py
supermarq/qcvv/base_experiment_test.py
supermarq/qcvv/conftest.py
supermarq/qcvv/irb.py
supermarq/qcvv/irb_test.py
supermarq/qcvv/su2.py
supermarq/qcvv/su2_test.py
supermarq/qcvv/xeb.py
supermarq/qcvv/xeb_test.py
supermarq-0.5.61.dist-info/METADATA
supermarq-0.5.61.dist-info/WHEEL
supermarq-0.5.61.dist-info/top_level.txt
supermarq-0.5.61.dist-info/RECORD
