Metadata-Version: 2.4
Name: Supermarq
Version: 0.5.61
Summary: Supermarq is a scalable, application-centric quantum benchmarking suite.
Author-email: Superstaq development team <superstaq@infleqtion.com>
License: Apache-2.0
Project-URL: homepage, https://github.com/Infleqtion/client-superstaq
Requires-Python: >=3.9.0
Requires-Dist: cirq-superstaq~=0.5.61
Requires-Dist: qiskit-superstaq~=0.5.61
Requires-Dist: scikit-learn>=1.0
Requires-Dist: seaborn>=0.13.2
Provides-Extra: dev
Requires-Dist: checks-superstaq~=0.5.61; extra == "dev"
